LICENSE.md
MANIFEST.in
README.md
requirements.txt
setup.cfg
setup.py
version.txt
m2translate/__init__.py
m2translate/core.py
m2translate/helpers.py
m2translate.egg-info/PKG-INFO
m2translate.egg-info/SOURCES.txt
m2translate.egg-info/dependency_links.txt
m2translate.egg-info/requires.txt
m2translate.egg-info/top_level.txt
m2translate/interfaces/__init__.py
m2translate/interfaces/store_connector.py
m2translate/store_connectors/__init__.py
m2translate/store_connectors/json_connector.py
m2translate/store_connectors/redis_connector.py