Metadata-Version: 1.1
Name: m2translate
Version: 1.0.3
Summary: M2Translate localization / translation package
Home-page: https://github.com/mdutkin/m2translate
Author: Maxim Dutkin
Author-email: max@dutkin.ru
License: MIT License
Platform: UNKNOWN
Classifier: Environment :: Web Environment
Classifier: Intended Audience :: Developers
Classifier: License :: OSI Approved :: MIT License
Classifier: Operating System :: OS Independent
Classifier: Programming Language :: Python :: 3
Classifier: Topic :: Software Development :: Localization
